NodejsApiDocInChinese/README.md
NodejsApiDocInChinese/__init__.py
NodejsApiDocInChinese/__main__.py
NodejsApiDocInChinese/file.epub
NodejsApiDocInChinese/index.html
NodejsApiDocInChinese/css/__init__.py
NodejsApiDocInChinese/css/annotations.css
NodejsApiDocInChinese/css/main.css
NodejsApiDocInChinese/css/normalize.css
NodejsApiDocInChinese/css/popup.css
NodejsApiDocInChinese/font/__init__.py
NodejsApiDocInChinese/font/fontello.eot
NodejsApiDocInChinese/font/fontello.svg
NodejsApiDocInChinese/font/fontello.ttf
NodejsApiDocInChinese/font/fontello.woff
NodejsApiDocInChinese/img/__init__.py
NodejsApiDocInChinese/img/annotator-glyph-sprite.png
NodejsApiDocInChinese/img/annotator-icon-sprite.png
NodejsApiDocInChinese/img/apple-touch-icon.png
NodejsApiDocInChinese/img/cancelfullscreen.png
NodejsApiDocInChinese/img/close.png
NodejsApiDocInChinese/img/fullscreen.png
NodejsApiDocInChinese/img/loader.gif
NodejsApiDocInChinese/img/menu-icon.png
NodejsApiDocInChinese/img/save.png
NodejsApiDocInChinese/img/saved.png
NodejsApiDocInChinese/img/settings-s.png
NodejsApiDocInChinese/img/settings.png
NodejsApiDocInChinese/img/star.png
NodejsApiDocInChinese/js/__init__.py
NodejsApiDocInChinese/js/epub.js
NodejsApiDocInChinese/js/epub.min.js
NodejsApiDocInChinese/js/epub.min.map
NodejsApiDocInChinese/js/hooks.min.js
NodejsApiDocInChinese/js/hooks.min.map
NodejsApiDocInChinese/js/reader.js
NodejsApiDocInChinese/js/reader.js.map
NodejsApiDocInChinese/js/reader.min.js
NodejsApiDocInChinese/js/reader.min.map
NodejsApiDocInChinese/js/hooks/__init__.py
NodejsApiDocInChinese/js/hooks/extensions/__init__.py
NodejsApiDocInChinese/js/hooks/extensions/highlight.js
NodejsApiDocInChinese/js/libs/__init__.py
NodejsApiDocInChinese/js/libs/jquery.min.js
NodejsApiDocInChinese/js/libs/localforage.min.js
NodejsApiDocInChinese/js/libs/screenfull.js
NodejsApiDocInChinese/js/libs/screenfull.min.js
NodejsApiDocInChinese/js/libs/zip.min.js
NodejsApiDocInChinese/js/plugins/__init__.py
nodejs_api_doc_in_chinese-2024.3.1.0.dist-info/METADATA
nodejs_api_doc_in_chinese-2024.3.1.0.dist-info/WHEEL
nodejs_api_doc_in_chinese-2024.3.1.0.dist-info/entry_points.txt
nodejs_api_doc_in_chinese-2024.3.1.0.dist-info/top_level.txt
nodejs_api_doc_in_chinese-2024.3.1.0.dist-info/RECORD
